naylence/fame/factory/__init__.py
naylence/fame/factory/expression_evaluator.py
naylence/fame/factory/expression_policy.py
naylence/fame/factory/expressions.py
naylence/fame/factory/extension_manager.py
naylence/fame/factory/resource_config.py
naylence/fame/factory/resource_factory.py
naylence/fame/factory/resource_factory_registry.py
naylence_factory-0.1.5.dist-info/METADATA
naylence_factory-0.1.5.dist-info/WHEEL
naylence_factory-0.1.5.dist-info/licenses/LICENSE
naylence_factory-0.1.5.dist-info/licenses/NOTICE
naylence_factory-0.1.5.dist-info/RECORD
